README.txt
setup.py
PaInt.egg-info/PKG-INFO
PaInt.egg-info/SOURCES.txt
PaInt.egg-info/dependency_links.txt
PaInt.egg-info/entry_points.txt
PaInt.egg-info/not-zip-safe
PaInt.egg-info/requires.txt
PaInt.egg-info/top_level.txt
paint/__init__.py
paint/main.py
paint/package.py
paint/pypi.py
paint/utils.py