Metadata-Version: 1.0
Name: PaInt
Version: 0.1
Summary: python PAckage INTrospection
Home-page: http://k0s.org/mozilla/hg/PaInt
Author: Jeff Hammel
Author-email: jhammel@mozilla.com
License: MPL
Platform: UNKNOWN
